Metadata-Version: 1.1
Name: sphinxcontrib-intertex
Version: 0.2.0
Summary: Like Intersphinx, but for Sphinx-built PDF documentation.
Home-page: https://github.com/mossblaser/intertex
Author: Jonathan Heathcote
Author-email: UNKNOWN
License: MIT
Keywords: sphinx documentation pdf latex reference
Platform: UNKNOWN
Classifier: Development Status :: 3 - Alpha
Classifier: Intended Audience :: Developers
Classifier: Operating System :: POSIX :: Linux
Classifier: Operating System :: Microsoft :: Windows
Classifier: Operating System :: MacOS
Classifier: Programming Language :: Python :: 3
